testpypipkgtest/__init__.py
testpypipkgtestjunk-0.1.1.dist-info/METADATA
testpypipkgtestjunk-0.1.1.dist-info/WHEEL
testpypipkgtestjunk-0.1.1.dist-info/top_level.txt
testpypipkgtestjunk-0.1.1.dist-info/RECORD
